{
	"order": [
		{
			"id": 0,
			"user": "mpzqwnn",
			"name": "1",
			"address": "1",
			"date1": "1",
			"date2": "1",
			"type": "1",
			"desc": "1111111111111111111111111111111111111111111111111111111111111111111111111111111111111111111",
			"Progress": true
		},
		{
			"id": 1,
			"user": "mpzqwnn",
			"name": "1",
			"address": "1",
			"date1": "1",
			"date2": "1",
			"type": "1",
			"desc": "1111111111111111111111111111111111111111111111111111111111111111111111111111111111111111111",
			"Progress": true
		},
		{
			"name": "1",
			"address": "1",
			"date1": "Sun Jun 04 2023 14:32:14",
			"date2": "2023-06-04T06:32:14.000Z",
			"type": "以旧换新",
			"desc": "1",
			"user": "mpzqwnn",
			"Progress": false,
			"id": 4
		}
	]
}